pip_project/fun.py
pip_project/__init__.py
pipfun-1.0.0.dist-info/WHEEL
pipfun-1.0.0.dist-info/METADATA
pipfun-1.0.0.dist-info/DESCRIPTION.rst
pipfun-1.0.0.dist-info/metadata.json
pipfun-1.0.0.dist-info/RECORD
pipfun-1.0.0.dist-info/top_level.txt
