Metadata-Version: 2.0
Name: pipfun
Version: 1.0.0
Summary: Does nothing much
Home-page: http://pypi.python.org/pypi/pipfun_v001/
Author: Umut Orman
Author-email: umutormans@gmail.com
License: UNKNOWN
Platform: UNKNOWN
